{
    "id": "xy12",
    "serieId": "xy",
    "name": "Evolution",
    "releaseDate": "2016-11-02",
    "cardCount": 108,
    "logo": "https://assets.tcgdex.net/de/xy/xy12/logo",
    "symbol": "https://assets.tcgdex.net/de/xy/xy12/symbol",
    "cards": [
        {
            "id": "xy12-1",
            "number": "1",
            "name": "Bisaflor EX",
            "illustrator": "Eske Yoshinob",
            "imageBase": "https://assets.tcgdex.net/de/xy/xy12/1"
        },
        {
            "id": "xy12-2",
            "number": "2",
            "name": "M-Bisaflor EX",
            "illustrator": "5ban Graphics",
            "imageBase": "https://assets.tcgdex.net/de/xy/xy12/2"
        },
        {
            "id": "xy12-3",
            "number": "3",
            "name": "Raupy",
            "illustrator": "Ken Sugimori",
            "imageBase": "https://assets.tcgdex.net/de/xy/xy12/3"
        },
        {
            "id": "xy12-4",
            "number": "4",
            "name": "Safcon",
            "illustrator": "Ken Sugimori",
            "imageBase": "https://assets.tcgdex.net/de/xy/xy12/4"
        },
        {
            "id": "xy12-5",
            "number": "5",
            "name": "Hornliu",
            "illustrator": "Mitsuhiro Arita",
            "imageBase": "https://assets.tcgdex.net/de/xy/xy12/5"
        },
        {
            "id": "xy12-6",
            "number": "6",
            "name": "Kokuna",
            "illustrator": "Keiji Kinebuchi",
            "imageBase": "https://assets.tcgdex.net/de/xy/xy12/6"
        },
        {
            "id": "xy12-7",
            "number": "7",
            "name": "Bibor",
            "illustrator": "Ken Sugimori",
            "imageBase": "https://assets.tcgdex.net/de/xy/xy12/7"
        },
        {
            "id": "xy12-8",
            "number": "8",
            "name": "Tangela",
            "illustrator": "Mitsuhiro Arita",
            "imageBase": "https://assets.tcgdex.net/de/xy/xy12/8"
        },
        {
            "id": "xy12-9",
            "number": "9",
            "name": "Glumanda",
            "illustrator": "Mitsuhiro Arita",
            "imageBase": "https://assets.tcgdex.net/de/xy/xy12/9"
        },
        {
            "id": "xy12-10",
            "number": "10",
            "name": "Glutexo",
            "illustrator": "Mitsuhiro Arita",
            "imageBase": "https://assets.tcgdex.net/de/xy/xy12/10"
        },
        {
            "id": "xy12-11",
            "number": "11",
            "name": "Glurak",
            "illustrator": "Mitsuhiro Arita",
            "imageBase": "https://assets.tcgdex.net/de/xy/xy12/11"
        },
        {
            "id": "xy12-12",
            "number": "12",
            "name": "Glurak EX",
            "illustrator": "PLANETA",
            "imageBase": "https://assets.tcgdex.net/de/xy/xy12/12"
        },
        {
            "id": "xy12-13",
            "number": "13",
            "name": "M-Glurak EX",
            "illustrator": "5ban Graphics",
            "imageBase": "https://assets.tcgdex.net/de/xy/xy12/13"
        },
        {
            "id": "xy12-14",
            "number": "14",
            "name": "Vulpix",
            "illustrator": "Ken Sugimori",
            "imageBase": "https://assets.tcgdex.net/de/xy/xy12/14"
        },
        {
            "id": "xy12-15",
            "number": "15",
            "name": "Vulnona",
            "illustrator": "Ken Sugimori",
            "imageBase": "https://assets.tcgdex.net/de/xy/xy12/15"
        },
        {
            "id": "xy12-16",
            "number": "16",
            "name": "Vulnona-TURBO",
            "illustrator": "5ban Graphics",
            "imageBase": "https://assets.tcgdex.net/de/xy/xy12/16"
        },
        {
            "id": "xy12-17",
            "number": "17",
            "name": "Fukano",
            "illustrator": "Ken Sugimori",
            "imageBase": "https://assets.tcgdex.net/de/xy/xy12/17"
        },
        {
            "id": "xy12-18",
            "number": "18",
            "name": "Arkani",
            "illustrator": "Ken Sugimori",
            "imageBase": "https://assets.tcgdex.net/de/xy/xy12/18"
        },
        {
            "id": "xy12-19",
            "number": "19",
            "name": "Ponita",
            "illustrator": "Ken Sugimori",
            "imageBase": "https://assets.tcgdex.net/de/xy/xy12/19"
        },
        {
            "id": "xy12-20",
            "number": "20",
            "name": "Magmar",
            "illustrator": "Ken Sugimori",
            "imageBase": "https://assets.tcgdex.net/de/xy/xy12/20"
        },
        {
            "id": "xy12-21",
            "number": "21",
            "name": "Turtok EX",
            "illustrator": "Eske Yoshinob",
            "imageBase": "https://assets.tcgdex.net/de/xy/xy12/21"
        },
        {
            "id": "xy12-22",
            "number": "22",
            "name": "M-Turtok EX",
            "illustrator": "5ban Graphics",
            "imageBase": "https://assets.tcgdex.net/de/xy/xy12/22"
        },
        {
            "id": "xy12-23",
            "number": "23",
            "name": "Quapsel",
            "illustrator": "Ken Sugimori",
            "imageBase": "https://assets.tcgdex.net/de/xy/xy12/23"
        },
        {
            "id": "xy12-24",
            "number": "24",
            "name": "Quaputzi",
            "illustrator": "Ken Sugimori",
            "imageBase": "https://assets.tcgdex.net/de/xy/xy12/24"
        },
        {
            "id": "xy12-25",
            "number": "25",
            "name": "Quappo",
            "illustrator": "Ken Sugimori",
            "imageBase": "https://assets.tcgdex.net/de/xy/xy12/25"
        },
        {
            "id": "xy12-26",
            "number": "26",
            "name": "Lahmus EX",
            "illustrator": "Ayaka Yoshida",
            "imageBase": "https://assets.tcgdex.net/de/xy/xy12/26"
        },
        {
            "id": "xy12-27",
            "number": "27",
            "name": "M-Lahmus EX",
            "illustrator": "5ban Graphics",
            "imageBase": "https://assets.tcgdex.net/de/xy/xy12/27"
        },
        {
            "id": "xy12-28",
            "number": "28",
            "name": "Jurob",
            "illustrator": "Ken Sugimori",
            "imageBase": "https://assets.tcgdex.net/de/xy/xy12/28"
        },
        {
            "id": "xy12-29",
            "number": "29",
            "name": "Jugong",
            "illustrator": "Mitsuhiro Arita",
            "imageBase": "https://assets.tcgdex.net/de/xy/xy12/29"
        },
        {
            "id": "xy12-30",
            "number": "30",
            "name": "Sterndu",
            "illustrator": "Keiji Kinebuchi",
            "imageBase": "https://assets.tcgdex.net/de/xy/xy12/30"
        },
        {
            "id": "xy12-31",
            "number": "31",
            "name": "Starmie",
            "illustrator": "Keiji Kinebuchi",
            "imageBase": "https://assets.tcgdex.net/de/xy/xy12/31"
        },
        {
            "id": "xy12-32",
            "number": "32",
            "name": "Starmie-TURBO",
            "illustrator": "5ban Graphics",
            "imageBase": "https://assets.tcgdex.net/de/xy/xy12/32"
        },
        {
            "id": "xy12-33",
            "number": "33",
            "name": "Karpador",
            "illustrator": "Mitsuhiro Arita",
            "imageBase": "https://assets.tcgdex.net/de/xy/xy12/33"
        },
        {
            "id": "xy12-34",
            "number": "34",
            "name": "Garados",
            "illustrator": "Mitsuhiro Arita",
            "imageBase": "https://assets.tcgdex.net/de/xy/xy12/34"
        },
        {
            "id": "xy12-35",
            "number": "35",
            "name": "Pikachu",
            "illustrator": "Mitsuhiro Arita",
            "imageBase": "https://assets.tcgdex.net/de/xy/xy12/35"
        },
        {
            "id": "xy12-36",
            "number": "36",
            "name": "Raichu",
            "illustrator": "Ken Sugimori",
            "imageBase": "https://assets.tcgdex.net/de/xy/xy12/36"
        },
        {
            "id": "xy12-37",
            "number": "37",
            "name": "Magnetilo",
            "illustrator": "Keiji Kinebuchi",
            "imageBase": "https://assets.tcgdex.net/de/xy/xy12/37"
        },
        {
            "id": "xy12-38",
            "number": "38",
            "name": "Magneton",
            "illustrator": "Keiji Kinebuchi",
            "imageBase": "https://assets.tcgdex.net/de/xy/xy12/38"
        },
        {
            "id": "xy12-39",
            "number": "39",
            "name": "Voltobal",
            "illustrator": "Keiji Kinebuchi",
            "imageBase": "https://assets.tcgdex.net/de/xy/xy12/39"
        },
        {
            "id": "xy12-40",
            "number": "40",
            "name": "Lektrobal",
            "illustrator": "Keiji Kinebuchi",
            "imageBase": "https://assets.tcgdex.net/de/xy/xy12/40"
        },
        {
            "id": "xy12-41",
            "number": "41",
            "name": "Elektek",
            "illustrator": "Ken Sugimori",
            "imageBase": "https://assets.tcgdex.net/de/xy/xy12/41"
        },
        {
            "id": "xy12-42",
            "number": "42",
            "name": "Zapdos",
            "illustrator": "Ken Sugimori",
            "imageBase": "https://assets.tcgdex.net/de/xy/xy12/42"
        },
        {
            "id": "xy12-43",
            "number": "43",
            "name": "Nidoran♂",
            "illustrator": "Ken Sugimori",
            "imageBase": "https://assets.tcgdex.net/de/xy/xy12/43"
        },
        {
            "id": "xy12-44",
            "number": "44",
            "name": "Nidorino",
            "illustrator": "Mitsuhiro Arita",
            "imageBase": "https://assets.tcgdex.net/de/xy/xy12/44"
        },
        {
            "id": "xy12-45",
            "number": "45",
            "name": "Nidoking",
            "illustrator": "Ken Sugimori",
            "imageBase": "https://assets.tcgdex.net/de/xy/xy12/45"
        },
        {
            "id": "xy12-46",
            "number": "46",
            "name": "Nidoking-TURBO",
            "illustrator": "5ban Graphics",
            "imageBase": "https://assets.tcgdex.net/de/xy/xy12/46"
        },
        {
            "id": "xy12-47",
            "number": "47",
            "name": "Nebulak",
            "illustrator": "Keiji Kinebuchi",
            "imageBase": "https://assets.tcgdex.net/de/xy/xy12/47"
        },
        {
            "id": "xy12-48",
            "number": "48",
            "name": "Alpollo",
            "illustrator": "Keiji Kinebuchi",
            "imageBase": "https://assets.tcgdex.net/de/xy/xy12/48"
        },
        {
            "id": "xy12-49",
            "number": "49",
            "name": "Traumato",
            "illustrator": "Ken Sugimori",
            "imageBase": "https://assets.tcgdex.net/de/xy/xy12/49"
        },
        {
            "id": "xy12-50",
            "number": "50",
            "name": "Smogon",
            "illustrator": "Mitsuhiro Arita",
            "imageBase": "https://assets.tcgdex.net/de/xy/xy12/50"
        },
        {
            "id": "xy12-51",
            "number": "51",
            "name": "Mewtu",
            "illustrator": "Ken Sugimori",
            "imageBase": "https://assets.tcgdex.net/de/xy/xy12/51"
        },
        {
            "id": "xy12-52",
            "number": "52",
            "name": "Mewtu EX",
            "illustrator": "Eske Yoshinob",
            "imageBase": "https://assets.tcgdex.net/de/xy/xy12/52"
        },
        {
            "id": "xy12-53",
            "number": "53",
            "name": "Mew",
            "illustrator": "Ken Sugimori",
            "imageBase": "https://assets.tcgdex.net/de/xy/xy12/53"
        },
        {
            "id": "xy12-54",
            "number": "54",
            "name": "Sandan",
            "illustrator": "Ken Sugimori",
            "imageBase": "https://assets.tcgdex.net/de/xy/xy12/54"
        },
        {
            "id": "xy12-55",
            "number": "55",
            "name": "Digda",
            "illustrator": "Keiji Kinebuchi",
            "imageBase": "https://assets.tcgdex.net/de/xy/xy12/55"
        },
        {
            "id": "xy12-56",
            "number": "56",
            "name": "Digdri",
            "illustrator": "Keiji Kinebuchi",
            "imageBase": "https://assets.tcgdex.net/de/xy/xy12/56"
        },
        {
            "id": "xy12-57",
            "number": "57",
            "name": "Machollo",
            "illustrator": "Mitsuhiro Arita",
            "imageBase": "https://assets.tcgdex.net/de/xy/xy12/57"
        },
        {
            "id": "xy12-58",
            "number": "58",
            "name": "Maschock",
            "illustrator": "Ken Sugimori",
            "imageBase": "https://assets.tcgdex.net/de/xy/xy12/58"
        },
        {
            "id": "xy12-59",
            "number": "59",
            "name": "Machomei",
            "illustrator": "Ken Sugimori",
            "imageBase": "https://assets.tcgdex.net/de/xy/xy12/59"
        },
        {
            "id": "xy12-60",
            "number": "60",
            "name": "Machomei-TURBO",
            "illustrator": "5ban Graphics",
            "imageBase": "https://assets.tcgdex.net/de/xy/xy12/60"
        },
        {
            "id": "xy12-61",
            "number": "61",
            "name": "Onix",
            "illustrator": "Ken Sugimori",
            "imageBase": "https://assets.tcgdex.net/de/xy/xy12/61"
        },
        {
            "id": "xy12-62",
            "number": "62",
            "name": "Nockchan",
            "illustrator": "Ken Sugimori",
            "imageBase": "https://assets.tcgdex.net/de/xy/xy12/62"
        },
        {
            "id": "xy12-63",
            "number": "63",
            "name": "Piepi",
            "illustrator": "Ken Sugimori",
            "imageBase": "https://assets.tcgdex.net/de/xy/xy12/63"
        },
        {
            "id": "xy12-64",
            "number": "64",
            "name": "Tauboss EX",
            "illustrator": "Eske Yoshinob",
            "imageBase": "https://assets.tcgdex.net/de/xy/xy12/64"
        },
        {
            "id": "xy12-65",
            "number": "65",
            "name": "M-Tauboss EX",
            "illustrator": "5ban Graphics",
            "imageBase": "https://assets.tcgdex.net/de/xy/xy12/65"
        },
        {
            "id": "xy12-66",
            "number": "66",
            "name": "Rattfratz",
            "illustrator": "Mitsuhiro Arita",
            "imageBase": "https://assets.tcgdex.net/de/xy/xy12/66"
        },
        {
            "id": "xy12-67",
            "number": "67",
            "name": "Rattikarl",
            "illustrator": "Ken Sugimori",
            "imageBase": "https://assets.tcgdex.net/de/xy/xy12/67"
        },
        {
            "id": "xy12-68",
            "number": "68",
            "name": "Porenta",
            "illustrator": "Ken Sugimori",
            "imageBase": "https://assets.tcgdex.net/de/xy/xy12/68"
        },
        {
            "id": "xy12-69",
            "number": "69",
            "name": "Dodu",
            "illustrator": "Mitsuhiro Arita",
            "imageBase": "https://assets.tcgdex.net/de/xy/xy12/69"
        },
        {
            "id": "xy12-70",
            "number": "70",
            "name": "Chaneira",
            "illustrator": "Ken Sugimori",
            "imageBase": "https://assets.tcgdex.net/de/xy/xy12/70"
        },
        {
            "id": "xy12-71",
            "number": "71",
            "name": "Porygon",
            "illustrator": "Tomoaki Imakuni",
            "imageBase": "https://assets.tcgdex.net/de/xy/xy12/71"
        },
        {
            "id": "xy12-72",
            "number": "72",
            "name": "Dragoran EX",
            "illustrator": "Ayaka Yoshida",
            "imageBase": "https://assets.tcgdex.net/de/xy/xy12/72"
        },
        {
            "id": "xy12-73",
            "number": "73",
            "name": "Turtoks Geistesbund",
            "illustrator": "5ban Graphics",
            "imageBase": "https://assets.tcgdex.net/de/xy/xy12/73"
        },
        {
            "id": "xy12-74",
            "number": "74",
            "name": "Rockos Durchhaltevermögen",
            "illustrator": "Ken Sugimori",
            "imageBase": "https://assets.tcgdex.net/de/xy/xy12/74"
        },
        {
            "id": "xy12-75",
            "number": "75",
            "name": "Gluraks Geistesbund",
            "illustrator": "5ban Graphics",
            "imageBase": "https://assets.tcgdex.net/de/xy/xy12/75"
        },
        {
            "id": "xy12-76",
            "number": "76",
            "name": "Rückentwicklungsspray",
            "illustrator": "Keiji Kinebuchi",
            "imageBase": "https://assets.tcgdex.net/de/xy/xy12/76"
        },
        {
            "id": "xy12-77",
            "number": "77",
            "name": "Energie-Zugewinn",
            "illustrator": "Keiji Kinebuchi",
            "imageBase": "https://assets.tcgdex.net/de/xy/xy12/77"
        },
        {
            "id": "xy12-78",
            "number": "78",
            "name": "Hyperheiler",
            "illustrator": "Keiji Kinebuchi",
            "imageBase": "https://assets.tcgdex.net/de/xy/xy12/78"
        },
        {
            "id": "xy12-79",
            "number": "79",
            "name": "Wartung",
            "illustrator": "Keiji Kinebuchi",
            "imageBase": "https://assets.tcgdex.net/de/xy/xy12/79"
        },
        {
            "id": "xy12-80",
            "number": "80",
            "name": "Mistys Entschlossenheit",
            "illustrator": "Ken Sugimori",
            "imageBase": "https://assets.tcgdex.net/de/xy/xy12/80"
        },
        {
            "id": "xy12-81",
            "number": "81",
            "name": "Tauboss' Geistesbund",
            "illustrator": "5ban Graphics",
            "imageBase": "https://assets.tcgdex.net/de/xy/xy12/81"
        },
        {
            "id": "xy12-82",
            "number": "82",
            "name": "Pokédex",
            "illustrator": "Keiji Kinebuchi",
            "imageBase": "https://assets.tcgdex.net/de/xy/xy12/82"
        },
        {
            "id": "xy12-83",
            "number": "83",
            "name": "Trank",
            "illustrator": "Keiji Kinebuchi",
            "imageBase": "https://assets.tcgdex.net/de/xy/xy12/83"
        },
        {
            "id": "xy12-84",
            "number": "84",
            "name": "Prof. Eichs Tipp",
            "illustrator": "Ken Sugimori",
            "imageBase": "https://assets.tcgdex.net/de/xy/xy12/84"
        },
        {
            "id": "xy12-85",
            "number": "85",
            "name": "Beleber",
            "illustrator": "Keiji Kinebuchi",
            "imageBase": "https://assets.tcgdex.net/de/xy/xy12/85"
        },
        {
            "id": "xy12-86",
            "number": "86",
            "name": "Lahmus' Geistesbund",
            "illustrator": "5ban Graphics",
            "imageBase": "https://assets.tcgdex.net/de/xy/xy12/86"
        },
        {
            "id": "xy12-87",
            "number": "87",
            "name": "Supertrank",
            "illustrator": "Keiji Kinebuchi",
            "imageBase": "https://assets.tcgdex.net/de/xy/xy12/87"
        },
        {
            "id": "xy12-88",
            "number": "88",
            "name": "Tausch",
            "illustrator": "Keiji Kinebuchi",
            "imageBase": "https://assets.tcgdex.net/de/xy/xy12/88"
        },
        {
            "id": "xy12-89",
            "number": "89",
            "name": "Bisaflors Geistesbund",
            "illustrator": "5ban Graphics",
            "imageBase": "https://assets.tcgdex.net/de/xy/xy12/89"
        },
        {
            "id": "xy12-90",
            "number": "90",
            "name": "Doppel-Farblos-Energie",
            "illustrator": "Keiji Kinebuchi",
            "imageBase": "https://assets.tcgdex.net/de/xy/xy12/90"
        },
        {
            "id": "xy12-91",
            "number": "91",
            "name": "Pflanze-Energie",
            "illustrator": null,
            "imageBase": "https://assets.tcgdex.net/de/xy/xy12/91"
        },
        {
            "id": "xy12-92",
            "number": "92",
            "name": "Feuer-Energie",
            "illustrator": null,
            "imageBase": "https://assets.tcgdex.net/de/xy/xy12/92"
        },
        {
            "id": "xy12-93",
            "number": "93",
            "name": "Wasser-Energie",
            "illustrator": null,
            "imageBase": "https://assets.tcgdex.net/de/xy/xy12/93"
        },
        {
            "id": "xy12-94",
            "number": "94",
            "name": "Elektro-Energie",
            "illustrator": null,
            "imageBase": "https://assets.tcgdex.net/de/xy/xy12/94"
        },
        {
            "id": "xy12-95",
            "number": "95",
            "name": "Psycho-Energie",
            "illustrator": null,
            "imageBase": "https://assets.tcgdex.net/de/xy/xy12/95"
        },
        {
            "id": "xy12-96",
            "number": "96",
            "name": "Kampf-Energie",
            "illustrator": null,
            "imageBase": "https://assets.tcgdex.net/de/xy/xy12/96"
        },
        {
            "id": "xy12-97",
            "number": "97",
            "name": "Finsternis-Energie",
            "illustrator": null,
            "imageBase": "https://assets.tcgdex.net/de/xy/xy12/97"
        },
        {
            "id": "xy12-98",
            "number": "98",
            "name": "Metall-Energie",
            "illustrator": null,
            "imageBase": "https://assets.tcgdex.net/de/xy/xy12/98"
        },
        {
            "id": "xy12-99",
            "number": "99",
            "name": "Feen-Energie",
            "illustrator": null,
            "imageBase": "https://assets.tcgdex.net/de/xy/xy12/99"
        },
        {
            "id": "xy12-100",
            "number": "100",
            "name": "M-Bisaflor EX",
            "illustrator": "5ban Graphics",
            "imageBase": "https://assets.tcgdex.net/de/xy/xy12/100"
        },
        {
            "id": "xy12-101",
            "number": "101",
            "name": "M-Glurak EX",
            "illustrator": "5ban Graphics",
            "imageBase": "https://assets.tcgdex.net/de/xy/xy12/101"
        },
        {
            "id": "xy12-102",
            "number": "102",
            "name": "M-Turtok EX",
            "illustrator": "5ban Graphics",
            "imageBase": "https://assets.tcgdex.net/de/xy/xy12/102"
        },
        {
            "id": "xy12-103",
            "number": "103",
            "name": "Mewtu EX",
            "illustrator": "Ryo Ueda",
            "imageBase": "https://assets.tcgdex.net/de/xy/xy12/103"
        },
        {
            "id": "xy12-104",
            "number": "104",
            "name": "Tauboss EX",
            "illustrator": "Ryo Ueda",
            "imageBase": "https://assets.tcgdex.net/de/xy/xy12/104"
        },
        {
            "id": "xy12-105",
            "number": "105",
            "name": "M-Tauboss EX",
            "illustrator": "5ban Graphics",
            "imageBase": "https://assets.tcgdex.net/de/xy/xy12/105"
        },
        {
            "id": "xy12-106",
            "number": "106",
            "name": "Dragoran EX",
            "illustrator": "Ryo Ueda",
            "imageBase": "https://assets.tcgdex.net/de/xy/xy12/106"
        },
        {
            "id": "xy12-107",
            "number": "107",
            "name": "Rockos Durchhaltevermögen",
            "illustrator": "Hitoshi Ariga",
            "imageBase": "https://assets.tcgdex.net/de/xy/xy12/107"
        },
        {
            "id": "xy12-108",
            "number": "108",
            "name": "Mistys Entschlossenheit",
            "illustrator": "Megumi Mizutani",
            "imageBase": "https://assets.tcgdex.net/de/xy/xy12/108"
        },
        {
            "id": "xy12-109",
            "number": "109",
            "name": "Kokowei",
            "illustrator": "Dr.Ooyama",
            "imageBase": "https://assets.tcgdex.net/de/xy/xy12/109"
        },
        {
            "id": "xy12-110",
            "number": "110",
            "name": "Fliegendes Pikachu",
            "illustrator": "Toshinao Aoki",
            "imageBase": "https://assets.tcgdex.net/de/xy/xy12/110"
        },
        {
            "id": "xy12-111",
            "number": "111",
            "name": "Surfendes Pikachu",
            "illustrator": "Toshinao Aoki",
            "imageBase": "https://assets.tcgdex.net/de/xy/xy12/111"
        },
        {
            "id": "xy12-112",
            "number": "112",
            "name": "Imakuni?s Dodu",
            "illustrator": "Imakuni?",
            "imageBase": "https://assets.tcgdex.net/de/xy/xy12/112"
        },
        {
            "id": "xy12-113",
            "number": "113",
            "name": "Hier kommt Team Rocket!",
            "illustrator": "Ken Sugimori",
            "imageBase": "https://assets.tcgdex.net/de/xy/xy12/113"
        }
    ]
}