{
    "illustrator": "Gakuji Nomoto",
    "series": [
        {
            "id": "base",
            "name": "Base",
            "releaseDate": "1999-01-09",
            "sets": [
                {
                    "id": "basep",
                    "name": "Wizards Black Star Promos",
                    "releaseDate": "1999-07-01",
                    "cards": [
                        {
                            "id": "basep-26",
                            "number": "26"
                        }
                    ]
                }
            ]
        }
    ]
}